axiomelectrus/__init__.py
axiomelectrus/core/__init__.py
axiomelectrus/core/client.py
axiomelectrus/core/collection.py
axiomelectrus/core/database.py
axiomelectrus/core/transactions.py
axiomelectrus/exception/__init__.py
axiomelectrus/exception/base.py
axiomelectrus/handler/__init__.py
axiomelectrus/handler/files.py
axiomelectrus/handler/schema.py
axiomelectrus/handler/filemanager/__init__.py
axiomelectrus/handler/filemanager/atomicoperation.py
axiomelectrus/handler/filemanager/backupmanager.py
axiomelectrus/handler/filemanager/checksumcalculator.py
axiomelectrus/handler/filemanager/jsonfilemanager.py
axiomelectrus/handler/filemanager/lockmanager.py
axiomelectrus/handler/filemanager/manager.py
axiomelectrus/handler/filemanager/metadata.py
axiomelectrus/handler/filemanager/versionmanager.py
axiomelectrus/partials/__init__.py
axiomelectrus/partials/delete.py
axiomelectrus/partials/find.py
axiomelectrus/partials/indexmanager.py
axiomelectrus/partials/insert.py
axiomelectrus/partials/objectId.py
axiomelectrus/partials/operators.py
axiomelectrus/partials/results.py
axiomelectrus/partials/update.py
axiomelectrus/synchronous/__init__.py
axiomelectrus/synchronous/core/__init__.py
axiomelectrus/synchronous/core/client.py
axiomelectrus/synchronous/core/collection.py
axiomelectrus/synchronous/core/database.py
axiomelectrus/synchronous/core/transactions.py
axiomelectrus/synchronous/partials/__init__.py
axiomelectrus/synchronous/partials/delete.py
axiomelectrus/synchronous/partials/find.py
axiomelectrus/synchronous/partials/insert.py
axiomelectrus/synchronous/partials/objectID.py
axiomelectrus/synchronous/partials/operators.py
axiomelectrus/synchronous/partials/result.py
axiomelectrus/synchronous/partials/update.py
axiomelectrus/synchronous/utils/__init__.py
axiomelectrus/synchronous/utils/aggregation.py
axiomelectrus/synchronous/utils/bulk.py
axiomelectrus/synchronous/utils/compator.py
axiomelectrus/synchronous/utils/distinct.py
axiomelectrus/utils/__init__.py
axiomelectrus-1.1.2.dist-info/licenses/LICENSE
axiomelectrus-1.1.2.dist-info/METADATA
axiomelectrus-1.1.2.dist-info/WHEEL
axiomelectrus-1.1.2.dist-info/top_level.txt
axiomelectrus-1.1.2.dist-info/RECORD
