Metadata-Version: 2.4
Name: axiomelectrus
Version: 1.1.2
Summary: Electrus is a lightweight, MongoDB-style asynchronous and synchronous database module designed for Python.
Home-page: https://github.com/axiomchronicles/electrus
Author: Pawan Kumar
Author-email: aegis.invincible@gmail.com
License: MIT
Project-URL: Documentation, https://github.com/axiomchronicles/electrus/wiki
Project-URL: Source, https://github.com/axiomchronicles/electrus
Project-URL: Tracker, https://github.com/axiomchronicles/electrus/issues
Project-URL: Changelog, https://github.com/axiomchronicles/electrus/releases
Keywords: database,nosql,json,mongodb,async,synchronous,lightweight,electrus,python-database,data-storage,indexing,file-based-db
Classifier: Development Status :: 3 - Alpha
Classifier: Intended Audience :: Developers
Classifier: Topic :: Database
Classifier: Topic :: Software Development :: Libraries
Classifier: License :: OSI Approved :: MIT License
Classifier: Operating System :: OS Independent
Classifier: Programming Language :: Python :: 3
Classifier: Programming Language :: Python :: 3.6
Classifier: Programming Language :: Python :: 3.7
Classifier: Programming Language :: Python :: 3.8
Classifier: Programming Language :: Python :: 3.9
Classifier: Programming Language :: Python :: 3.10
Classifier: Programming Language :: Python :: 3.11
Requires-Python: >=3.6
License-File: LICENSE
Requires-Dist: aiofiles>=0.6.0
Requires-Dist: numpy>=1.20.0
Requires-Dist: filelock>=3.0.0
Dynamic: author
Dynamic: author-email
Dynamic: classifier
Dynamic: description
Dynamic: description-content-type
Dynamic: home-page
Dynamic: keywords
Dynamic: license
Dynamic: license-file
Dynamic: project-url
Dynamic: requires-dist
Dynamic: requires-python
Dynamic: summary
